stencil_maker/__init__.py
stencil_maker/__main__.py
stencil_maker/core.py
stencil_maker/server.py
stencil_maker/static/main.js
stencil_maker/static/style.css
stencil_maker/templates/index.html
stencil_maker/templates/result-fragment.html
stencil_maker-0.1.1.dist-info/METADATA
stencil_maker-0.1.1.dist-info/WHEEL
stencil_maker-0.1.1.dist-info/entry_points.txt
stencil_maker-0.1.1.dist-info/licenses/LICENSE
stencil_maker-0.1.1.dist-info/RECORD
