Metadata-Version: 2.3
Name: stencil-maker
Version: 0.1.1
Summary: Generate an image for a text stencil
Author-email: mamg22 <45301823+mamg22@users.noreply.github.com>
License-File: LICENSE
Classifier: Development Status :: 3 - Alpha
Classifier: License :: OSI Approved :: MIT License
Classifier: Programming Language :: Python :: 3
Classifier: Programming Language :: Python :: 3 :: Only
Classifier: Programming Language :: Python :: 3.8
Classifier: Programming Language :: Python :: 3.9
Classifier: Programming Language :: Python :: 3.10
Classifier: Programming Language :: Python :: 3.11
Classifier: Programming Language :: Python :: 3.12
Classifier: Topic :: Multimedia :: Graphics
Requires-Python: >=3.8
Requires-Dist: pillow>=10.3.0
Requires-Dist: python-dotenv>=1.0.1
Provides-Extra: server
Requires-Dist: flask>=3.0.3; extra == 'server'
